{
  "ACCES_KEY_ID": "fakeMyKeyId",
  "AWS_REGION": "us-east-1",
  "DATABASE_MARIADB": "emacommerce",
  "DATABASE_URL": "file:./dev.db",
  "DB_URL": "http://dynamodb:8000",
  "HOST_MARIADB": "mariadb",
  "JWT_SECRET": "asda124jadaslzcx12358ad124ASDJs",
  "KAFKA_CLIENTID": "ms-payments",
  "KAFKA_CONSUMER": "ms-payments-comsumer",
  "KAFKA_URL": "kafka:29092",
  "MQTT_URL": "mqtt://mqtt:1883",
  "MYSQL_DATABASE": "emacommerce",
  "MYSQL_HOST": "mysql",
  "MYSQL_PASSWORD": "emacommerce",
  "MYSQL_PORT": 3306,
  "MYSQL_ROOT_PASSWORD": "rootPass",
  "MYSQL_USER": "emacommerce",
  "NATS_SERVER_URL": "nats://nats:4222",
  "PASSWORD_MARIADB": "emacommerce",
  "PORT": 3000,
  "PORT_MARIADB": 3306,
  "PROM_PASS": "admin",
  "PROM_USER": "admin",
  "RABBITMQ_DEFAULT_PASS": "password",
  "RABBITMQ_DEFAULT_USER": "user",
  "RMQ_QUEUE": "auth_queue",
  "RMQ_SERVER_URL": "amqp://user:password@rabbitmq:5672",
  "SECRET_ACCESS_KEY": "fakeSecretAccessKey",
  "USERNAME_MARIADB": "emacommerce"
}